ergal/__init__.py
ergal/cli.py
ergal/profile.py
ergal/utils.py
ergal-1.1.2.dist-info/LICENSE
ergal-1.1.2.dist-info/WHEEL
ergal-1.1.2.dist-info/METADATA
ergal-1.1.2.dist-info/RECORD
