Metadata-Version: 2.1
Name: ergal
Version: 1.1.2
Summary: The Elegant and Readable General API Library
Home-page: UNKNOWN
License: MIT
Author: Elliott Maguire
Author-email: me@elliott-m.com
Requires-Python: >=3.7,<4.0
Classifier: License :: OSI Approved :: MIT License
Classifier: Programming Language :: Python :: 3
Classifier: Programming Language :: Python :: 3.7
Requires-Dist: requests (>=2.21,<3.0)
Requires-Dist: xmltodict (>=0.12.0,<0.13.0)
